pycharting/__init__.py
pycharting/api/__init__.py
pycharting/api/interface.py
pycharting/api/routes.py
pycharting/core/__init__.py
pycharting/core/lifecycle.py
pycharting/core/server.py
pycharting/data/__init__.py
pycharting/data/ingestion.py
pycharting/web/__init__.py
pycharting/web/static/demo.html
pycharting/web/static/js/chart.js
pycharting/web/static/js/sync.js
pycharting/web/static/js/viewport.js
pycharting/web/static/multi-chart-demo.html
pycharting/web/static/viewport-demo.html
pycharting-0.2.14.dist-info/METADATA
pycharting-0.2.14.dist-info/WHEEL
pycharting-0.2.14.dist-info/RECORD
