Metadata-Version: 2.1
Name: pycharting
Version: 0.2.14
Summary: High-performance financial charting library for OHLC data visualization with technical indicators
Home-page: https://github.com/alihaskar/pycharting
License: MIT
Keywords: charting,finance,ohlc,technical-indicators,trading,visualization
Author: ali askar
Author-email: 26202651+alihaskar@users.noreply.github.com
Requires-Python: >=3.12,<4.0
Classifier: Development Status :: 3 - Alpha
Classifier: Intended Audience :: Developers
Classifier: Intended Audience :: Financial and Insurance Industry
Classifier: License :: OSI Approved :: MIT License
Classifier: Programming Language :: Python :: 3
Classifier: Programming Language :: Python :: 3.12
Classifier: Topic :: Office/Business :: Financial
Classifier: Topic :: Scientific/Engineering :: Visualization
Requires-Dist: fastapi (>=0.115.0,<1.0.0)
Requires-Dist: numpy (>=1.26.0,<3.0.0)
Requires-Dist: pandas (>=2.2.0,<3.0.0)
Requires-Dist: pyarrow (>=22.0.0,<23.0.0)
Requires-Dist: pydantic (>=2.7.0,<3.0.0)
Requires-Dist: pytz (>=2024.1,<2026.0)
Requires-Dist: uvicorn[standard] (>=0.24.0,<1.0.0)
Project-URL: Repository, https://github.com/alihaskar/pycharting
